{
	"name": "Event sheet 1",
	"events": [
		{
			"eventType": "include",
			"includeSheet": "ePlayer"
		},
		{
			"eventType": "group",
			"disabled": false,
			"title": "Keluar Masuk",
			"description": "",
			"isActiveOnStart": true,
			"children": [
				{
					"eventType": "group",
					"disabled": false,
					"title": "Masuk",
					"description": "",
					"isActiveOnStart": true,
					"children": [
						{
							"eventType": "block",
							"conditions": [
								{
									"id": "on-collision-with-another-object",
									"objectClass": "Spr_PMPEnter",
									"sid": 703874890132652,
									"parameters": {
										"object": "Spr_Player_MCBella"
									}
								}
							],
							"actions": [
								{
									"id": "go-to-layout",
									"objectClass": "System",
									"sid": 736684934041711,
									"parameters": {
										"layout": "Gedung1_Floor1"
									}
								}
							],
							"sid": 841385892701904
						},
						{
							"eventType": "block",
							"conditions": [
								{
									"id": "on-collision-with-another-object",
									"objectClass": "Spr_PembayaranEnter",
									"sid": 437476858693069,
									"parameters": {
										"object": "Spr_Player_MCBella"
									}
								}
							],
							"actions": [
								{
									"id": "go-to-layout",
									"objectClass": "System",
									"sid": 883019132956243,
									"parameters": {
										"layout": "Gedung1_Keuangan"
									}
								}
							],
							"sid": 799334337383870
						},
						{
							"eventType": "block",
							"conditions": [
								{
									"id": "on-collision-with-another-object",
									"objectClass": "Spr_RegistrasiEnter",
									"sid": 163920420114255,
									"parameters": {
										"object": "Spr_Player_MCBella"
									}
								}
							],
							"actions": [
								{
									"id": "go-to-layout",
									"objectClass": "System",
									"sid": 116983984826229,
									"parameters": {
										"layout": "Gedung1_Pendaftaran"
									}
								}
							],
							"sid": 637225464652942
						}
					],
					"sid": 438746312538314
				},
				{
					"eventType": "group",
					"disabled": false,
					"title": "Keluar",
					"description": "",
					"isActiveOnStart": true,
					"children": [
						{
							"eventType": "block",
							"conditions": [
								{
									"id": "on-collision-with-another-object",
									"objectClass": "Spr_PMPExit",
									"sid": 626003379247881,
									"parameters": {
										"object": "Spr_Player_MCBella"
									}
								}
							],
							"actions": [
								{
									"id": "go-to-layout",
									"objectClass": "System",
									"sid": 539423933662646,
									"parameters": {
										"layout": "BL_Frontb"
									}
								}
							],
							"sid": 698583541076854
						},
						{
							"eventType": "block",
							"conditions": [
								{
									"id": "on-collision-with-another-object",
									"objectClass": "Spr_PembayaranExit",
									"sid": 106222316633253,
									"parameters": {
										"object": "Spr_Player_MCBella"
									}
								}
							],
							"actions": [
								{
									"id": "go-to-layout",
									"objectClass": "System",
									"sid": 323685560856332,
									"parameters": {
										"layout": "Gedung1_Floor1"
									}
								}
							],
							"sid": 694089714277718
						},
						{
							"eventType": "block",
							"conditions": [
								{
									"id": "on-collision-with-another-object",
									"objectClass": "Spr_RegistrasiExit",
									"sid": 217669157342178,
									"parameters": {
										"object": "Spr_Player_MCBella"
									}
								}
							],
							"actions": [
								{
									"id": "go-to-layout",
									"objectClass": "System",
									"sid": 236708259694210,
									"parameters": {
										"layout": "Gedung1_Floor1"
									}
								}
							],
							"sid": 584019821826352
						}
					],
					"sid": 702433798524505
				}
			],
			"sid": 656115054298476
		},
		{
			"eventType": "block",
			"conditions": [
				{
					"id": "on-start-of-layout",
					"objectClass": "System",
					"sid": 648812828777838
				}
			],
			"actions": [
				{
					"id": "stop-all",
					"objectClass": "Audio",
					"sid": 445624405442573
				},
				{
					"id": "play",
					"objectClass": "Audio",
					"sid": 403375400649457,
					"parameters": {
						"audio-file": "wind",
						"loop": "looping",
						"volume": "-5",
						"stereo-pan": "0",
						"tag-optional": "\"\""
					}
				}
			],
			"sid": 810992187145357
		}
	],
	"sid": 932350374578162
}